circuit_visualization
circuits_to_truth_tables
features_to_circuits
sequences_to_features
test
