Metadata-Version: 1.1
Name: SYNBICT
Version: 1.5.2
Summary: Synthetic Biology Curation Tools (SYNBICT)
Home-page: https://github.com/SD2E/SYNBICT
Author: Nicholas Roehner
Author-email: nicholasroehner@gmail.com
License: UNKNOWN
Download-URL: https://github.com/SD2E/SYNBICT/archive/refs/tags/v1.5.2.tar.gz
Platform: UNKNOWN
Classifier: Programming Language :: Python :: 3 :: Only
